pygamehack/__init__.py
pygamehack/c.pypy37-pp73-win_amd64.pyd
pygamehack/code.py
pygamehack/reclassnet.py
pygamehack/struct.py
pygamehack/struct_file.py
pygamehack/struct_meta.py
pygamehack/struct_parser.py
pygamehack/variable.py
pygamehack/gdb/__init__.py
pygamehack/gdb/gdb.py
pygamehack/gdb/io.py
pygamehack/gdb/parser.py
pygamehack_gui/__init__.py
pygamehack_gui/address_view.py
pygamehack_gui/app_view.py
pygamehack_gui/class_view.py
pygamehack_gui/main.py
pygamehack_gui/process_dialog.py
pygamehack_gui/variable_view.py
pygamehack_gui/core/__init__.py
pygamehack_gui/core/action.py
pygamehack_gui/core/animation.py
pygamehack_gui/core/popup.py
pygamehack_gui/core/tree_view.py
pygamehack-1.0.11.dist-info/LICENSE.txt
pygamehack-1.0.11.dist-info/METADATA
pygamehack-1.0.11.dist-info/WHEEL
pygamehack-1.0.11.dist-info/top_level.txt
pygamehack-1.0.11.dist-info/RECORD
