Metadata-Version: 2.1
Name: pygamehack
Version: 1.0.11
Summary: Python game hacking interface
Home-page: https://github.com/sentrip/pygamehack
Author: Djordje Pepic
Author-email: djordje.m.pepic@gmail.com
License: UNKNOWN
Platform: UNKNOWN
Requires-Python: >=3.7
License-File: LICENSE.txt
Requires-Dist: pybind11 (>=2.6.2)
Provides-Extra: test
Requires-Dist: pytest ; extra == 'test'
